yuanlanlab_tool/__init__.py
yuanlanlab_tool/_build.py
yuanlanlab_tool/_help.py
yuanlanlab_tool-0.0.0.6.dist-info/METADATA
yuanlanlab_tool-0.0.0.6.dist-info/WHEEL
yuanlanlab_tool-0.0.0.6.dist-info/top_level.txt
yuanlanlab_tool-0.0.0.6.dist-info/RECORD
