Metadata-Version: 2.4
Name: yuanlanlab_tool
Version: 0.0.0.6
Summary: 空间链接：https://space.bilibili.com/3546564903569609
Author: 元蓝先生@B站
License: This work is licensed under a Creative Commons Attribution-NonCommercial-NoDerivatives 4.0 International License.
Dynamic: author
Dynamic: license
Dynamic: summary
